{
  "Bloody Darryl The Strapped | The Professionals": {
    "name": "Bloody Darryl The Strapped | The Professionals",
    "nameId": 1087079
  },
  "'Blueberries' Buckshot | NSWC SEAL": {
    "name": "'Blueberries' Buckshot | NSWC SEAL",
    "nameId": 1083601
  },
  "'Two Times' McCoy | TACP Cavalry": {
    "name": "'Two Times' McCoy | TACP Cavalry",
    "nameId": 1083492
  },
  "Cmdr. Mae 'Dead Cold' Jamison | SWAT": {
    "name": "Cmdr. Mae 'Dead Cold' Jamison | SWAT",
    "nameId": 1083460
  },
  "1st Lieutenant Farlow | SWAT": {
    "name": "1st Lieutenant Farlow | SWAT",
    "nameId": 1083508
  },
  "John 'Van Healen' Kask | SWAT": {
    "name": "John 'Van Healen' Kask | SWAT",
    "nameId": 1083667
  },
  "Bio-Haz Specialist | SWAT": {
    "name": "Bio-Haz Specialist | SWAT",
    "nameId": 1083660
  },
  "Sergeant Bombson | SWAT": {
    "name": "Sergeant Bombson | SWAT",
    "nameId": 1083663
  },
  "Chem-Haz Specialist | SWAT": {
    "name": "Chem-Haz Specialist | SWAT",
    "nameId": 1083710
  },
  "Rezan the Redshirt | Sabre": {
    "name": "Rezan the Redshirt | Sabre",
    "nameId": 1083611
  },
  "Sir Bloody Miami Darryl | The Professionals": {
    "name": "Sir Bloody Miami Darryl | The Professionals",
    "nameId": 1083593
  },
  "Safecracker Voltzmann | The Professionals": {
    "name": "Safecracker Voltzmann | The Professionals",
    "nameId": 1083649
  },
  "Little Kev | The Professionals": {
    "name": "Little Kev | The Professionals",
    "nameId": 1083547
  },
  "Getaway Sally | The Professionals": {
    "name": "Getaway Sally | The Professionals",
    "nameId": 1083625
  },
  "Number K | The Professionals": {
    "name": "Number K | The Professionals",
    "nameId": 1083439
  },
  "Sir Bloody Silent Darryl | The Professionals": {
    "name": "Sir Bloody Silent Darryl | The Professionals",
    "nameId": 1083550
  },
  "Sir Bloody Skullhead Darryl | The Professionals": {
    "name": "Sir Bloody Skullhead Darryl | The Professionals",
    "nameId": 1083536
  },
  "Sir Bloody Darryl Royale | The Professionals": {
    "name": "Sir Bloody Darryl Royale | The Professionals",
    "nameId": 1083409
  },
  "Sir Bloody Loudmouth Darryl | The Professionals": {
    "name": "Sir Bloody Loudmouth Darryl | The Professionals",
    "nameId": 1083461
  },
  "Sous-Lieutenant Medic | Gendarmerie Nationale": {
    "name": "Sous-Lieutenant Medic | Gendarmerie Nationale",
    "nameId": 1087132
  },
  "Chem-Haz Capitaine | Gendarmerie Nationale": {
    "name": "Chem-Haz Capitaine | Gendarmerie Nationale",
    "nameId": 1086830
  },
  "Chef d'Escadron Rouchard | Gendarmerie Nationale": {
    "name": "Chef d'Escadron Rouchard | Gendarmerie Nationale",
    "nameId": 1086972
  },
  "Aspirant | Gendarmerie Nationale": {
    "name": "Aspirant | Gendarmerie Nationale",
    "nameId": 1087333
  },
  "Officer Jacques Beltram | Gendarmerie Nationale": {
    "name": "Officer Jacques Beltram | Gendarmerie Nationale",
    "nameId": 1087175
  },
  "Lieutenant 'Tree Hugger' Farlow | SWAT": {
    "name": "Lieutenant 'Tree Hugger' Farlow | SWAT",
    "nameId": 1087206
  },
  "Cmdr. Davida 'Goggles' Fernandez | SEAL Frogman": {
    "name": "Cmdr. Davida 'Goggles' Fernandez | SEAL Frogman",
    "nameId": 1086948
  },
  "Cmdr. Frank 'Wet Sox' Baroud | SEAL Frogman": {
    "name": "Cmdr. Frank 'Wet Sox' Baroud | SEAL Frogman",
    "nameId": 1087071
  },
  "Lieutenant Rex Krikey | SEAL Frogman": {
    "name": "Lieutenant Rex Krikey | SEAL Frogman",
    "nameId": 1087229
  },
  "Elite Trapper Solman | Guerrilla Warfare": {
    "name": "Elite Trapper Solman | Guerrilla Warfare",
    "nameId": 1087035
  },
  "Crasswater The Forgotten | Guerrilla Warfare": {
    "name": "Crasswater The Forgotten | Guerrilla Warfare",
    "nameId": 1087106
  },
  "Arno The Overgrown | Guerrilla Warfare": {
    "name": "Arno The Overgrown | Guerrilla Warfare",
    "nameId": 1087162
  },
  "Col. Mangos Dabisi | Guerrilla Warfare": {
    "name": "Col. Mangos Dabisi | Guerrilla Warfare",
    "nameId": 1086989
  },
  "Vypa Sista of the Revolution | Guerrilla Warfare": {
    "name": "Vypa Sista of the Revolution | Guerrilla Warfare",
    "nameId": 1086847
  },
  "Trapper Aggressor | Guerrilla Warfare": {
    "name": "Trapper Aggressor | Guerrilla Warfare",
    "nameId": 1087168
  },
  "'Medium Rare' Crasswater | Guerrilla Warfare": {
    "name": "'Medium Rare' Crasswater | Guerrilla Warfare",
    "nameId": 1086985
  },
  "Trapper | Guerrilla Warfare": {
    "name": "Trapper | Guerrilla Warfare",
    "nameId": 1087035
  },
  "Ground Rebel  | Elite Crew": {
    "name": "Ground Rebel  | Elite Crew",
    "nameId": 1073911
  },
  "Osiris | Elite Crew": {
    "name": "Osiris | Elite Crew",
    "nameId": 1073894
  },
  "Prof. Shahmat | Elite Crew": {
    "name": "Prof. Shahmat | Elite Crew",
    "nameId": 1074066
  },
  "The Elite Mr. Muhlik | Elite Crew": {
    "name": "The Elite Mr. Muhlik | Elite Crew",
    "nameId": 1073882
  },
  "Jungle Rebel | Elite Crew": {
    "name": "Jungle Rebel | Elite Crew",
    "nameId": 1087614
  },
  "Soldier | Phoenix": {
    "name": "Soldier | Phoenix",
    "nameId": 1083658
  },
  "Enforcer | Phoenix": {
    "name": "Enforcer | Phoenix",
    "nameId": 1073865
  },
  "Slingshot | Phoenix": {
    "name": "Slingshot | Phoenix",
    "nameId": 1074084
  },
  "Street Soldier | Phoenix": {
    "name": "Street Soldier | Phoenix",
    "nameId": 1083658
  },
  "Operator | FBI SWAT": {
    "name": "Operator | FBI SWAT",
    "nameId": 1074026
  },
  "Markus Delrow | FBI HRT": {
    "name": "Markus Delrow | FBI HRT",
    "nameId": 1073910
  },
  "Michael Syfers  | FBI Sniper": {
    "name": "Michael Syfers  | FBI Sniper",
    "nameId": 1074098
  },
  "Special Agent Ava | FBI": {
    "name": "Special Agent Ava | FBI",
    "nameId": 1074063
  },
  "3rd Commando Company | KSK": {
    "name": "3rd Commando Company | KSK",
    "nameId": 1073957
  },
  "Seal Team 6 Soldier | NSWC SEAL": {
    "name": "Seal Team 6 Soldier | NSWC SEAL",
    "nameId": 1074058
  },
  "Buckshot | NSWC SEAL": {
    "name": "Buckshot | NSWC SEAL",
    "nameId": 1083601
  },
  "'Two Times' McCoy | USAF TACP": {
    "name": "'Two Times' McCoy | USAF TACP",
    "nameId": 1073912
  },
  "Lt. Commander Ricksaw | NSWC SEAL": {
    "name": "Lt. Commander Ricksaw | NSWC SEAL",
    "nameId": 1073908
  },
  "Primeiro Tenente | Brazilian 1st Battalion": {
    "name": "Primeiro Tenente | Brazilian 1st Battalion",
    "nameId": 1087221
  },
  "Dragomir | Sabre": {
    "name": "Dragomir | Sabre",
    "nameId": 1083659
  },
  "Maximus | Sabre": {
    "name": "Maximus | Sabre",
    "nameId": 1073952
  },
  "Rezan The Ready | Sabre": {
    "name": "Rezan The Ready | Sabre",
    "nameId": 1073887
  },
  "Blackwolf | Sabre": {
    "name": "Blackwolf | Sabre",
    "nameId": 1074053
  },
  "'The Doctor' Romanov | Sabre": {
    "name": "'The Doctor' Romanov | Sabre",
    "nameId": 1073944
  },
  "Dragomir | Sabre Footsoldier": {
    "name": "Dragomir | Sabre Footsoldier",
    "nameId": 1083659
  },
  "B Squadron Officer | SAS": {
    "name": "B Squadron Officer | SAS",
    "nameId": 1073899
  },
  "D Squadron Officer | NZSAS": {
    "name": "D Squadron Officer | NZSAS",
    "nameId": 1087228
  },
  "Operation Payback Pass": {
    "name": "Operation Payback Pass",
    "nameId": 19216
  },
  "Operation Bloodhound Access Pass": {
    "name": "Operation Bloodhound Access Pass",
    "nameId": 14375
  },
  "Operation Hydra Access Pass": {
    "name": "Operation Hydra Access Pass",
    "nameId": 3512
  },
  "Operation Shattered Web Premium Pass": {
    "name": "Operation Shattered Web Premium Pass",
    "nameId": 1073859
  },
  "Katowice 2019 Viewer Pass": {
    "name": "Katowice 2019 Viewer Pass",
    "nameId": 194862
  },
  "Berlin 2019 Viewer Pass": {
    "name": "Berlin 2019 Viewer Pass",
    "nameId": 874615
  },
  "Berlin 2019 Viewer Pass + 3 Souvenir Tokens": {
    "name": "Berlin 2019 Viewer Pass + 3 Souvenir Tokens",
    "nameId": 874615
  },
  "Berlin 2019 Souvenir Token": {
    "name": "Berlin 2019 Souvenir Token",
    "nameId": 874615
  },
  "Civil Protection Pin": {
    "name": "Civil Protection Pin",
    "nameId": 1079212
  },
  "Sustenance! Pin": {
    "name": "Sustenance! Pin",
    "nameId": 1079224
  },
  "Vortigaunt Pin": {
    "name": "Vortigaunt Pin",
    "nameId": 1079203
  }
}